py_smi/__init__.py
py_smi/_modidx.py
py_smi/core.py
python_smi-0.0.2.dist-info/LICENSE
python_smi-0.0.2.dist-info/METADATA
python_smi-0.0.2.dist-info/WHEEL
python_smi-0.0.2.dist-info/entry_points.txt
python_smi-0.0.2.dist-info/top_level.txt
python_smi-0.0.2.dist-info/RECORD
