Metadata-Version: 2.1
Name: python-smi
Version: 0.0.2
Summary: Convenient access to `pynvml` (the library behind `nvidia-smi`)
Home-page: https://github.com/AnswerDotAI/py-smi
Author: Jeremy Howard
Author-email: info@fast.ai
License: Apache Software License 2.0
Keywords: nbdev jupyter notebook python
Classifier: Development Status :: 4 - Beta
Classifier: Intended Audience :: Developers
Classifier: Natural Language :: English
Classifier: Programming Language :: Python :: 3.9
Classifier: Programming Language :: Python :: 3.10
Classifier: Programming Language :: Python :: 3.11
Classifier: Programming Language :: Python :: 3.12
Classifier: License :: OSI Approved :: Apache Software License
Requires-Python: >=3.9
License-File: LICENSE
Requires-Dist: fastcore
Requires-Dist: nvidia-ml-py
Requires-Dist: psutil
Provides-Extra: dev
